pyls_memestra/__init__.py
pyls_memestra/plugin.py
tests/__init__.py
tests/test_plugin.py
pyls_memestra-0.0.16.dist-info/LICENSE
pyls_memestra-0.0.16.dist-info/METADATA
pyls_memestra-0.0.16.dist-info/WHEEL
pyls_memestra-0.0.16.dist-info/entry_points.txt
pyls_memestra-0.0.16.dist-info/top_level.txt
pyls_memestra-0.0.16.dist-info/RECORD
