Metadata-Version: 2.1
Name: pyls-memestra
Version: 0.0.16
Summary: Memestra plugin for the Python Language Server
Home-page: https://github.com/QuantStack/pyls-memestra
Author: marimeireles
Author-email: mariana@psychonautgirl.space
License: UNKNOWN
Platform: UNKNOWN
Classifier: Environment :: Console
Classifier: Intended Audience :: Developers
Classifier: License :: OSI Approved :: BSD License
Classifier: Natural Language :: English
Classifier: Programming Language :: Python :: 2
Classifier: Programming Language :: Python :: 2.7
Classifier: Programming Language :: Python :: 3
Classifier: Programming Language :: Python :: 3.4
Classifier: Programming Language :: Python :: 3.5
Classifier: Programming Language :: Python :: 3.6
License-File: LICENSE
Requires-Dist: python-lsp-server
Requires-Dist: memestra
Requires-Dist: Deprecated
